setup.py
src/fc_vfemp1/BVP.py
src/fc_vfemp1/FEM.py
src/fc_vfemp1/FEMOptV3.py
src/fc_vfemp1/FEMbase.py
src/fc_vfemp1/FEMtools.py
src/fc_vfemp1/__init__.py
src/fc_vfemp1/common.py
src/fc_vfemp1/lib.py
src/fc_vfemp1/matplotlib.py
src/fc_vfemp1/operators.py
src/fc_vfemp1/sparse.py
src/fc_vfemp1/sys.py
src/fc_vfemp1.egg-info/PKG-INFO
src/fc_vfemp1.egg-info/SOURCES.txt
src/fc_vfemp1.egg-info/dependency_links.txt
src/fc_vfemp1.egg-info/requires.txt
src/fc_vfemp1.egg-info/top_level.txt
src/fc_vfemp1/examples/BVPCondenser2D01.py
src/fc_vfemp1/examples/BVPElasticity2D01.py
src/fc_vfemp1/examples/BVPElasticity3D01.py
src/fc_vfemp1/examples/BVPElectrostatic2D01.py
src/fc_vfemp1/examples/BVPHeatAndFlowVelocity2D01.py
src/fc_vfemp1/examples/BVPHeatAndFlowVelocity3D01.py
src/fc_vfemp1/examples/BVPStationaryConvectionDiffusion2D01.py
src/fc_vfemp1/examples/BVPStationaryConvectionDiffusion3D01.py
src/fc_vfemp1/examples/__init__.py
src/fc_vfemp1/examples/examples.py
src/fc_vfemp1/examples/set_examples.py
src/fc_vfemp1/geodir/2d/options01_data.geo
src/fc_vfemp1/geodir/2d/shape_functions.geo
src/fc_vfemp1/geodir/2d/square4holes6dom.geo
src/fc_vfemp1/geodir/3d/cube6.geo
src/fc_vfemp1/geodir/3d/cylinder3dom.geo
src/fc_vfemp1/geodir/3d/cylinder3holes.geo
src/fc_vfemp1/geodir/3d/cylinderkey.geo