Metadata-Version: 1.1
Name: fc-vfemp1
Version: 0.0.3
Summary: Solve scalar and vector Boundary Value Problems by P1-Lagrange ﬁnite element method in any space dimension
Home-page: http://www.math.univ-paris13.fr/~cuvelier/software
Author: Francois Cuvelier
Author-email: cuvelier@math.univ-paris13.fr
License: BSD
Platform: Linux
Classifier: Topic :: Scientific/Engineering
